{
  "event_id": "d4a88bf8-5ea4-421e-a019-d593dd11d985",
  "source_id": "00cb110a-ba04-410b-a1e6-6870fc6da9e1",
  "set": "default",
  "annotations": [
    {
      "start_time": 1811.779,
      "end_time": 1815.819,
      "annotation": [
        {
          "text": " Umezurike:",
          "bold": true
        },
        {
          "text": "  there's a spot that we'll come to the to the question"
        }
      ],
      "tags": [],
      "uuid": "edd7cf48-c382-4a8b-abe9-29934382d835"
    }
  ]
}