{
  "event_id": "d4a88bf8-5ea4-421e-a019-d593dd11d985",
  "source_id": "00cb110a-ba04-410b-a1e6-6870fc6da9e1",
  "set": "default",
  "annotations": [
    {
      "start_time": 4328.39,
      "end_time": 4352.64,
      "annotation": [
        {
          "text": " Chinwuba:",
          "bold": true
        },
        {
          "text": "  And um it's a a cross-fertilization of ideas, as well. Because Nollywood is growing. Because at their fingertips they have Hollywood. They have Bollywood. They have other experiences. And so they are able to see what is happening there. And say, why can't I do this? Why can't I replicate this? This is in Bollywood in India. We can do this as well."
        }
      ],
      "tags": [],
      "uuid": "7db0671c-12bd-4300-bd77-e952c917ea39"
    }
  ]
}