{
  "event_id": "d4a88bf8-5ea4-421e-a019-d593dd11d985",
  "source_id": "00cb110a-ba04-410b-a1e6-6870fc6da9e1",
  "set": "default",
  "annotations": [
    {
      "start_time": 3493.88,
      "end_time": 3521.619,
      "annotation": [
        {
          "text": " Chinwuba:",
          "bold": true
        },
        {
          "text": "  This program, writer-in-residence program, has given me the focus I need to, you know, abjure other things and focus on my work. And I actually have a novel or two in the making. That are, you know, approaching the denouement, if I can put it that way. So I'm now looking for an agent and a publisher. So, very soon you will. You will get it. Thank you."
        }
      ],
      "tags": [],
      "uuid": "a8f5c61e-bf60-4e60-ba12-00f8d867b137"
    }
  ]
}