{
  "event_id": "d4a88bf8-5ea4-421e-a019-d593dd11d985",
  "source_id": "00cb110a-ba04-410b-a1e6-6870fc6da9e1",
  "set": "default",
  "annotations": [
    {
      "start_time": 4976.119,
      "end_time": 4980.25,
      "annotation": [
        {
          "text": " Chinwuba:",
          "bold": true
        },
        {
          "text": "  So, government is aware. Yesterday, they are closing schools. Ah, they say security is"
        }
      ],
      "tags": [],
      "uuid": "8b7a52aa-caf9-44e0-9225-0c6fdacbcb0f"
    }
  ]
}