{
  "event_id": "d4a88bf8-5ea4-421e-a019-d593dd11d985",
  "source_id": "00cb110a-ba04-410b-a1e6-6870fc6da9e1",
  "set": "default",
  "annotations": [
    {
      "start_time": 441.42,
      "end_time": 445.61,
      "annotation": [
        {
          "text": " Sonuga:",
          "bold": true
        },
        {
          "text": "  Thank you, and I just wanted to say that it's an honor to share"
        }
      ],
      "tags": [],
      "uuid": "52a9fc25-82e1-4053-93d8-ac0bc66500ca"
    }
  ]
}