{
  "event_id": "d4a88bf8-5ea4-421e-a019-d593dd11d985",
  "source_id": "00cb110a-ba04-410b-a1e6-6870fc6da9e1",
  "set": "default",
  "annotations": [
    {
      "start_time": 3238.01,
      "end_time": 3267,
      "annotation": [
        {
          "text": " Chinwuba:",
          "bold": true
        },
        {
          "text": "  It should be recalled that early last week Freeman Fort was attacked by unknown persons during a period of prolonged blackouts. The aging perimeter walls were easily knocked down, enabling the inmates to escape to freedom. Three female guards sustained injuries, nonfatal. The presidency has set up a panel to investigate the incident."
        }
      ],
      "tags": [],
      "uuid": "204bf874-ef05-4638-bef5-684948919fe5"
    }
  ]
}