{
  "event_id": "d4a88bf8-5ea4-421e-a019-d593dd11d985",
  "source_id": "00cb110a-ba04-410b-a1e6-6870fc6da9e1",
  "set": "default",
  "annotations": [
    {
      "start_time": 81.769,
      "end_time": 85.98,
      "annotation": [
        {
          "text": " O'Driscoll:",
          "bold": true
        },
        {
          "text": "  musicians, cultural activists, and performers to learn about,"
        }
      ],
      "tags": [],
      "uuid": "d3311666-b4cc-49fc-9889-a471623f80d7"
    }
  ]
}