{
  "event_id": "d4a88bf8-5ea4-421e-a019-d593dd11d985",
  "source_id": "00cb110a-ba04-410b-a1e6-6870fc6da9e1",
  "set": "default",
  "annotations": [
    {
      "start_time": 2630.15,
      "end_time": 2634.179,
      "annotation": [
        {
          "text": " Chinwuba:",
          "bold": true
        },
        {
          "text": "  Which means they don't care. Which means the the government can't catch them. Can't do anything"
        }
      ],
      "tags": [],
      "uuid": "620e6598-1ed6-4640-9aad-e412c9755db3"
    }
  ]
}